DMseg_test/__init__.py
DMseg_test/dmseg.py
DMseg_test-0.0.3.dist-info/LICENSE
DMseg_test-0.0.3.dist-info/METADATA
DMseg_test-0.0.3.dist-info/WHEEL
DMseg_test-0.0.3.dist-info/top_level.txt
DMseg_test-0.0.3.dist-info/RECORD
