Metadata-Version: 2.1
Name: DMseg-test
Version: 0.0.3
Summary: Python package for DMseg
Author: aaa bbb
Author-email: <youremail@email.com>
License: MIT
Keywords: python,DNA methylation,Differentially methylated regions
Platform: UNKNOWN
Classifier: Topic :: Scientific/Engineering :: Bio-Informatics
License-File: LICENSE
Requires-Dist: pandas
Requires-Dist: numpy
